Metadata-Version: 2.1
Name: Log4Shell
Version: 1.0.3
Summary: A Python package for tracking IP addresses and their locations.
Home-page: https://github.com/ishanoshada/Log4Shell
Author: Ishan Oshada
Author-email: ishan.kodithuwakku.official@email.com
Classifier: Programming Language :: Python :: 3
Classifier: License :: OSI Approved :: MIT License
Classifier: Operating System :: OS Independent
License-File: LICENSE
Requires-Dist: requests
